{
  "response": {
    "script": {
      "-id": "youtube-hd-fjdmkanbdloodhegphphhklnjfngoffa",
      "#text": "var ythdlog = () => {};;var ythderror = () => {};"
    },
    "header": {
      "resultCode": "00",
      "resultMsg": "정상적으로 처리되었습니다.",
      "requestParameter": {
        "dietSeCode": "254004"
      }
    },
    "body": {
      "items": {
        "item": [
          {
            "cntntsChargerEsntlNm": {
              "#cdata-section": " 관리자 "
            },
            "cntntsNo": {
              "#cdata-section": " 89482 "
            },
            "cntntsRdcnt": {
              "#cdata-section": " 8 "
            },
            "cntntsSj": {
              "#cdata-section": " 조상의 지혜가 담긴 정월대보름 음식! "
            },
            "dietNm": {
              "#cdata-section": " 조상의 지혜가 담긴 정월대보름 음식! "
            },
            "fdNm": {
              "#cdata-section": " 오곡밥 "
            },
            "registDt": {
              "#cdata-section": " 2015-02-10 "
            },
            "rtnFileSeCode": {
              "#cdata-section": " 185002 "
            },
            "rtnFileSn": {
              "#cdata-section": " 1 "
            },
            "rtnImageDc": {
              "#cdata-section": " http://www.nongsaro.go.kr/cms_contents/114/89482_MF_ATTACH_01_TMB.jpg "
            },
            "rtnImgSeCode": {
              "#cdata-section": " 209001 "
            },
            "rtnOrginlFileNm": {
              "#cdata-section": " 9_0.jpg "
            },
            "rtnStreFileNm": {
              "#cdata-section": " 89482_MF_ATTACH_01.jpg "
            },
            "rtnThumbFileNm": {
              "#cdata-section": " 89482_MF_ATTACH_01_TMB.jpg "
            }
          },
          {
            "cntntsChargerEsntlNm": {
              "#cdata-section": " 관리자 "
            },
            "cntntsNo": {
              "#cdata-section": " 89481 "
            },
            "cntntsRdcnt": {
              "#cdata-section": " 12 "
            },
            "cntntsSj": {
              "#cdata-section": " 춘곤증을 이기고 새 봄의 미각을 돋우는 음식 "
            },
            "dietNm": {
              "#cdata-section": " 춘곤증을 이기고 새 봄의 미각을 돋우는 음식 "
            },
            "fdNm": {
              "#cdata-section": " 갓김치 "
            },
            "registDt": {
              "#cdata-section": " 2015-02-10 "
            },
            "rtnFileSeCode": {
              "#cdata-section": " 185002 "
            },
            "rtnFileSn": {
              "#cdata-section": " 1 "
            },
            "rtnImageDc": {
              "#cdata-section": " http://www.nongsaro.go.kr/cms_contents/114/89481_MF_ATTACH_01_TMB.jpg "
            },
            "rtnImgSeCode": {
              "#cdata-section": " 209001 "
            },
            "rtnOrginlFileNm": {
              "#cdata-section": " 10_0.jpg "
            },
            "rtnStreFileNm": {
              "#cdata-section": " 89481_MF_ATTACH_01.jpg "
            },
            "rtnThumbFileNm": {
              "#cdata-section": " 89481_MF_ATTACH_01_TMB.jpg "
            }
          },
          {
            "cntntsChargerEsntlNm": {
              "#cdata-section": " 관리자 "
            },
            "cntntsNo": {
              "#cdata-section": " 89480 "
            },
            "cntntsRdcnt": {
              "#cdata-section": " 1 "
            },
            "cntntsSj": {
              "#cdata-section": " 봄철 입맛 돋우는 음식 씀바귀나물, 취나물 "
            },
            "dietNm": {
              "#cdata-section": " 봄철 입맛 돋우는 음식 씀바귀나물, 취나물 "
            },
            "fdNm": {
              "#cdata-section": " 씀바귀취나물 "
            },
            "registDt": {
              "#cdata-section": " 2015-02-10 "
            },
            "rtnFileSeCode": {
              "#cdata-section": " 185002 "
            },
            "rtnFileSn": {
              "#cdata-section": " 1 "
            },
            "rtnImageDc": {
              "#cdata-section": " http://www.nongsaro.go.kr/cms_contents/114/89480_MF_ATTACH_01_TMB.jpg "
            },
            "rtnImgSeCode": {
              "#cdata-section": " 209001 "
            },
            "rtnOrginlFileNm": {
              "#cdata-section": " 11_0.jpg "
            },
            "rtnStreFileNm": {
              "#cdata-section": " 89480_MF_ATTACH_01.jpg "
            },
            "rtnThumbFileNm": {
              "#cdata-section": " 89480_MF_ATTACH_01_TMB.jpg "
            }
          },
          {
            "cntntsChargerEsntlNm": {
              "#cdata-section": " 관리자 "
            },
            "cntntsNo": {
              "#cdata-section": " 89479 "
            },
            "cntntsRdcnt": {
              "#cdata-section": " 12 "
            },
            "cntntsSj": {
              "#cdata-section": " 장모의 솜씨로 차린 백년손님, 사위 첫 생일상 "
            },
            "dietNm": {
              "#cdata-section": " 장모의 솜씨로 차린 백년손님, 사위 첫 생일상 "
            },
            "fdNm": {
              "#cdata-section": " 생일상 "
            },
            "registDt": {
              "#cdata-section": " 2015-02-10 "
            },
            "rtnFileSeCode": {
              "#cdata-section": " 185002 "
            },
            "rtnFileSn": {
              "#cdata-section": " 1 "
            },
            "rtnImageDc": {
              "#cdata-section": " http://www.nongsaro.go.kr/cms_contents/114/89479_MF_ATTACH_01_TMB.jpg "
            },
            "rtnImgSeCode": {
              "#cdata-section": " 209001 "
            },
            "rtnOrginlFileNm": {
              "#cdata-section": " 16_0.jpg "
            },
            "rtnStreFileNm": {
              "#cdata-section": " 89479_MF_ATTACH_01.jpg "
            },
            "rtnThumbFileNm": {
              "#cdata-section": " 89479_MF_ATTACH_01_TMB.jpg "
            }
          },
          {
            "cntntsChargerEsntlNm": {
              "#cdata-section": " 관리자 "
            },
            "cntntsNo": {
              "#cdata-section": " 89478 "
            },
            "cntntsRdcnt": {
              "#cdata-section": " 3 "
            },
            "cntntsSj": {
              "#cdata-section": " 식탁에 핀 향기로운 봄꽃 두릅 "
            },
            "dietNm": {
              "#cdata-section": " 식탁에 핀 향기로운 봄꽃 두릅 "
            },
            "fdNm": {
              "#cdata-section": " 녹두입힌두릅적 "
            },
            "registDt": {
              "#cdata-section": " 2015-02-10 "
            },
            "rtnFileSeCode": {
              "#cdata-section": " 185002 "
            },
            "rtnFileSn": {
              "#cdata-section": " 1 "
            },
            "rtnImageDc": {
              "#cdata-section": " http://www.nongsaro.go.kr/cms_contents/114/89478_MF_ATTACH_01_TMB.jpg "
            },
            "rtnImgSeCode": {
              "#cdata-section": " 209001 "
            },
            "rtnOrginlFileNm": {
              "#cdata-section": " 17_0.jpg "
            },
            "rtnStreFileNm": {
              "#cdata-section": " 89478_MF_ATTACH_01.jpg "
            },
            "rtnThumbFileNm": {
              "#cdata-section": " 89478_MF_ATTACH_01_TMB.jpg "
            }
          },
          {
            "cntntsChargerEsntlNm": {
              "#cdata-section": " 관리자 "
            },
            "cntntsNo": {
              "#cdata-section": " 89477 "
            },
            "cntntsRdcnt": {
              "#cdata-section": " 1 "
            },
            "cntntsSj": {
              "#cdata-section": " 오감만족 오미자 음료(창면)와 쑥굴리 "
            },
            "dietNm": {
              "#cdata-section": " 오감만족 오미자 음료(창면)와 쑥굴리 "
            },
            "fdNm": {
              "#cdata-section": " 창면 "
            },
            "registDt": {
              "#cdata-section": " 2015-02-10 "
            },
            "rtnFileSeCode": {
              "#cdata-section": " 185002 "
            },
            "rtnFileSn": {
              "#cdata-section": " 1 "
            },
            "rtnImageDc": {
              "#cdata-section": " http://www.nongsaro.go.kr/cms_contents/114/89477_MF_ATTACH_01_TMB.jpg "
            },
            "rtnImgSeCode": {
              "#cdata-section": " 209001 "
            },
            "rtnOrginlFileNm": {
              "#cdata-section": " 20_0.jpg "
            },
            "rtnStreFileNm": {
              "#cdata-section": " 89477_MF_ATTACH_01.jpg "
            },
            "rtnThumbFileNm": {
              "#cdata-section": " 89477_MF_ATTACH_01_TMB.jpg "
            }
          },
          {
            "cntntsChargerEsntlNm": {
              "#cdata-section": " 관리자 "
            },
            "cntntsNo": {
              "#cdata-section": " 89476 "
            },
            "cntntsRdcnt": {
              "#cdata-section": " 1 "
            },
            "cntntsSj": {
              "#cdata-section": " 임금님이 드시던 귀한 물고기 '웅어' "
            },
            "dietNm": {
              "#cdata-section": " 임금님이 드시던 귀한 물고기 '웅어' "
            },
            "fdNm": {
              "#cdata-section": " 웅어감정 "
            },
            "registDt": {
              "#cdata-section": " 2015-02-10 "
            },
            "rtnFileSeCode": {
              "#cdata-section": " 185002 "
            },
            "rtnFileSn": {
              "#cdata-section": " 1 "
            },
            "rtnImageDc": {
              "#cdata-section": " http://www.nongsaro.go.kr/cms_contents/114/89476_MF_ATTACH_01_TMB.jpg "
            },
            "rtnImgSeCode": {
              "#cdata-section": " 209001 "
            },
            "rtnOrginlFileNm": {
              "#cdata-section": " 23_0.jpg "
            },
            "rtnStreFileNm": {
              "#cdata-section": " 89476_MF_ATTACH_01.jpg "
            },
            "rtnThumbFileNm": {
              "#cdata-section": " 89476_MF_ATTACH_01_TMB.jpg "
            }
          },
          {
            "cntntsChargerEsntlNm": {
              "#cdata-section": " 관리자 "
            },
            "cntntsNo": {
              "#cdata-section": " 89475 "
            },
            "cntntsRdcnt": {
              "#cdata-section": " 1 "
            },
            "cntntsSj": {
              "#cdata-section": " 단오에 즐기는 별미, 망개떡 "
            },
            "dietNm": {
              "#cdata-section": " 단오에 즐기는 별미, 망개떡 "
            },
            "fdNm": {
              "#cdata-section": " 망개떡 "
            },
            "registDt": {
              "#cdata-section": " 2015-02-10 "
            },
            "rtnFileSeCode": {
              "#cdata-section": " 185002 "
            },
            "rtnFileSn": {
              "#cdata-section": " 1 "
            },
            "rtnImageDc": {
              "#cdata-section": " http://www.nongsaro.go.kr/cms_contents/114/89475_MF_ATTACH_01_TMB.jpg "
            },
            "rtnImgSeCode": {
              "#cdata-section": " 209001 "
            },
            "rtnOrginlFileNm": {
              "#cdata-section": " 24_0.jpg "
            },
            "rtnStreFileNm": {
              "#cdata-section": " 89475_MF_ATTACH_01.jpg "
            },
            "rtnThumbFileNm": {
              "#cdata-section": " 89475_MF_ATTACH_01_TMB.jpg "
            }
          },
          {
            "cntntsChargerEsntlNm": {
              "#cdata-section": " 관리자 "
            },
            "cntntsNo": {
              "#cdata-section": " 89474 "
            },
            "cntntsRdcnt": {
              "#cdata-section": " 4 "
            },
            "cntntsSj": {
              "#cdata-section": " 오감을 즐기며 먹는 쌈 "
            },
            "dietNm": {
              "#cdata-section": " 오감을 즐기며 먹는 쌈 "
            },
            "fdNm": {
              "#cdata-section": " 오곡 참취쌈밥 "
            },
            "registDt": {
              "#cdata-section": " 2015-02-10 "
            },
            "rtnFileSeCode": {
              "#cdata-section": " 185002 "
            },
            "rtnFileSn": {
              "#cdata-section": " 1 "
            },
            "rtnImageDc": {
              "#cdata-section": " http://www.nongsaro.go.kr/cms_contents/114/89474_MF_ATTACH_01_TMB.jpg "
            },
            "rtnImgSeCode": {
              "#cdata-section": " 209001 "
            },
            "rtnOrginlFileNm": {
              "#cdata-section": " 26_0.jpg "
            },
            "rtnStreFileNm": {
              "#cdata-section": " 89474_MF_ATTACH_01.jpg "
            },
            "rtnThumbFileNm": {
              "#cdata-section": " 89474_MF_ATTACH_01_TMB.jpg "
            }
          },
          {
            "cntntsChargerEsntlNm": {
              "#cdata-section": " 관리자 "
            },
            "cntntsNo": {
              "#cdata-section": " 89473 "
            },
            "cntntsRdcnt": {
              "#cdata-section": " 4 "
            },
            "cntntsSj": {
              "#cdata-section": " 음력 7월7일은 칠석(七夕) 견우와 직녀의 애틋한 마음을 기리며 먹는 절식 만나기 "
            },
            "dietNm": {
              "#cdata-section": " 음력 7월7일은 칠석(七夕) 견우와 직녀의 애틋한 마음을 기리며 먹는 절식 만나기 "
            },
            "fdNm": {
              "#cdata-section": " 호박생면닭칼국수, "
            },
            "registDt": {
              "#cdata-section": " 2015-02-10 "
            },
            "rtnFileSeCode": {
              "#cdata-section": " 185002 "
            },
            "rtnFileSn": {
              "#cdata-section": " 1 "
            },
            "rtnImageDc": {
              "#cdata-section": " http://www.nongsaro.go.kr/cms_contents/114/89473_MF_ATTACH_01_TMB.jpg "
            },
            "rtnImgSeCode": {
              "#cdata-section": " 209001 "
            },
            "rtnOrginlFileNm": {
              "#cdata-section": " 28_0.jpg "
            },
            "rtnStreFileNm": {
              "#cdata-section": " 89473_MF_ATTACH_01.jpg "
            },
            "rtnThumbFileNm": {
              "#cdata-section": " 89473_MF_ATTACH_01_TMB.jpg "
            }
          },
          {
            "cntntsChargerEsntlNm": {
              "#cdata-section": " 관리자 "
            },
            "cntntsNo": {
              "#cdata-section": " 89472 "
            },
            "cntntsRdcnt": {
              "#cdata-section": " 6 "
            },
            "cntntsSj": {
              "#cdata-section": " 8월 18일은 쌀데이 농부의 손을 88번 거쳐야 식탁에 오르는 영양과 정성이 가득 담긴 쌀, 맛있게 즐기기 "
            },
            "dietNm": {
              "#cdata-section": " 8월 18일은 쌀데이 농부의 손을 88번 거쳐야 식탁에 오르는 영양과 정성이 가득 담긴 쌀, 맛있게 즐기기 "
            },
            "fdNm": {
              "#cdata-section": " 버섯영양돌솥밥 "
            },
            "registDt": {
              "#cdata-section": " 2015-02-10 "
            },
            "rtnFileSeCode": {
              "#cdata-section": " 185002 "
            },
            "rtnFileSn": {
              "#cdata-section": " 1 "
            },
            "rtnImageDc": {
              "#cdata-section": " http://www.nongsaro.go.kr/cms_contents/114/89472_MF_ATTACH_01_TMB.jpg "
            },
            "rtnImgSeCode": {
              "#cdata-section": " 209001 "
            },
            "rtnOrginlFileNm": {
              "#cdata-section": " 31_0.jpg "
            },
            "rtnStreFileNm": {
              "#cdata-section": " 89472_MF_ATTACH_01.jpg "
            },
            "rtnThumbFileNm": {
              "#cdata-section": " 89472_MF_ATTACH_01_TMB.jpg "
            }
          },
          {
            "cntntsChargerEsntlNm": {
              "#cdata-section": " 관리자 "
            },
            "cntntsNo": {
              "#cdata-section": " 89471 "
            },
            "cntntsRdcnt": {
              "#cdata-section": " 1 "
            },
            "cntntsSj": {
              "#cdata-section": " 송편과 탕국 송편과 탕국 "
            },
            "dietNm": {
              "#cdata-section": " 송편과 탕국 송편과 탕국 "
            },
            "fdNm": {
              "#cdata-section": " 감자송편 "
            },
            "registDt": {
              "#cdata-section": " 2015-02-10 "
            },
            "rtnFileSeCode": {
              "#cdata-section": " 185002 "
            },
            "rtnFileSn": {
              "#cdata-section": " 1 "
            },
            "rtnImageDc": {
              "#cdata-section": " http://www.nongsaro.go.kr/cms_contents/114/89471_MF_ATTACH_01_TMB.jpg "
            },
            "rtnImgSeCode": {
              "#cdata-section": " 209001 "
            },
            "rtnOrginlFileNm": {
              "#cdata-section": " 32_0.jpg "
            },
            "rtnStreFileNm": {
              "#cdata-section": " 89471_MF_ATTACH_01.jpg "
            },
            "rtnThumbFileNm": {
              "#cdata-section": " 89471_MF_ATTACH_01_TMB.jpg "
            }
          },
          {
            "cntntsChargerEsntlNm": {
              "#cdata-section": " 관리자 "
            },
            "cntntsNo": {
              "#cdata-section": " 89470 "
            },
            "cntntsRdcnt": {
              "#cdata-section": " 1 "
            },
            "cntntsSj": {
              "#cdata-section": " 가족과 함께하는 연말연시 홈파티! "
            },
            "dietNm": {
              "#cdata-section": " 가족과 함께하는 연말연시 홈파티! "
            },
            "fdNm": {
              "#cdata-section": " 연근스프 "
            },
            "registDt": {
              "#cdata-section": " 2015-02-10 "
            },
            "rtnFileSeCode": {
              "#cdata-section": " 185002 "
            },
            "rtnFileSn": {
              "#cdata-section": " 1 "
            },
            "rtnImageDc": {
              "#cdata-section": " http://www.nongsaro.go.kr/cms_contents/114/89470_MF_ATTACH_01_TMB.jpg "
            },
            "rtnImgSeCode": {
              "#cdata-section": " 209001 "
            },
            "rtnOrginlFileNm": {
              "#cdata-section": " 33_0.jpg "
            },
            "rtnStreFileNm": {
              "#cdata-section": " 89470_MF_ATTACH_01.jpg "
            },
            "rtnThumbFileNm": {
              "#cdata-section": " 89470_MF_ATTACH_01_TMB.jpg "
            }
          },
          {
            "cntntsChargerEsntlNm": {
              "#cdata-section": " 관리자 "
            },
            "cntntsNo": {
              "#cdata-section": " 89469 "
            },
            "cntntsRdcnt": {
              "#cdata-section": " 1 "
            },
            "cntntsSj": {
              "#cdata-section": " 봄이 오는 길목에서.. <향긋한 하루를 열어주는 봄나물 한상> "
            },
            "dietNm": {
              "#cdata-section": " 봄이 오는 길목에서.. <향긋한 하루를 열어주는 봄나물 한상> "
            },
            "fdNm": {
              "#cdata-section": " 달래장 콩나물밥 "
            },
            "registDt": {
              "#cdata-section": " 2015-02-10 "
            },
            "rtnFileSeCode": {
              "#cdata-section": " 185002 "
            },
            "rtnFileSn": {
              "#cdata-section": " 1 "
            },
            "rtnImageDc": {
              "#cdata-section": " http://www.nongsaro.go.kr/cms_contents/114/89469_MF_ATTACH_01_TMB.png "
            },
            "rtnImgSeCode": {
              "#cdata-section": " 209001 "
            },
            "rtnOrginlFileNm": {
              "#cdata-section": " 36_0.png "
            },
            "rtnStreFileNm": {
              "#cdata-section": " 89469_MF_ATTACH_01.png "
            },
            "rtnThumbFileNm": {
              "#cdata-section": " 89469_MF_ATTACH_01_TMB.png "
            }
          },
          {
            "cntntsChargerEsntlNm": {
              "#cdata-section": " 관리자 "
            },
            "cntntsNo": {
              "#cdata-section": " 89468 "
            },
            "cntntsRdcnt": {
              "#cdata-section": " 2 "
            },
            "cntntsSj": {
              "#cdata-section": " 부모님을 위한 원데이 쉐프 "
            },
            "dietNm": {
              "#cdata-section": " 부모님을 위한 원데이 쉐프 "
            },
            "fdNm": {
              "#cdata-section": " 연근칩샐러드 "
            },
            "registDt": {
              "#cdata-section": " 2015-02-10 "
            },
            "rtnFileSeCode": {
              "#cdata-section": " 185002 "
            },
            "rtnFileSn": {
              "#cdata-section": " 1 "
            },
            "rtnImageDc": {
              "#cdata-section": " http://www.nongsaro.go.kr/cms_contents/114/89468_MF_ATTACH_01_TMB.png "
            },
            "rtnImgSeCode": {
              "#cdata-section": " 209001 "
            },
            "rtnOrginlFileNm": {
              "#cdata-section": " 37_0.png "
            },
            "rtnStreFileNm": {
              "#cdata-section": " 89468_MF_ATTACH_01.png "
            },
            "rtnThumbFileNm": {
              "#cdata-section": " 89468_MF_ATTACH_01_TMB.png "
            }
          },
          {
            "cntntsChargerEsntlNm": {
              "#cdata-section": " 관리자 "
            },
            "cntntsNo": {
              "#cdata-section": " 89467 "
            },
            "cntntsRdcnt": {
              "#cdata-section": " 3 "
            },
            "cntntsSj": {
              "#cdata-section": " 우리 농산물로 만든 건강한 간식 "
            },
            "dietNm": {
              "#cdata-section": " 우리 농산물로 만든 건강한 간식 "
            },
            "fdNm": {
              "#cdata-section": " 보리계란빵 "
            },
            "registDt": {
              "#cdata-section": " 2015-02-10 "
            },
            "rtnFileSeCode": {
              "#cdata-section": " 185002 "
            },
            "rtnFileSn": {
              "#cdata-section": " 1 "
            },
            "rtnImageDc": {
              "#cdata-section": " http://www.nongsaro.go.kr/cms_contents/114/89467_MF_ATTACH_01_TMB.png "
            },
            "rtnImgSeCode": {
              "#cdata-section": " 209001 "
            },
            "rtnOrginlFileNm": {
              "#cdata-section": " 38_0.png "
            },
            "rtnStreFileNm": {
              "#cdata-section": " 89467_MF_ATTACH_01.png "
            },
            "rtnThumbFileNm": {
              "#cdata-section": " 89467_MF_ATTACH_01_TMB.png "
            }
          },
          {
            "cntntsChargerEsntlNm": {
              "#cdata-section": " 관리자 "
            },
            "cntntsNo": {
              "#cdata-section": " 89466 "
            },
            "cntntsRdcnt": {
              "#cdata-section": " 2 "
            },
            "cntntsSj": {
              "#cdata-section": " 건강의 기본 피를 맑게 하는 식품 "
            },
            "dietNm": {
              "#cdata-section": " 건강의 기본 피를 맑게 하는 식품 "
            },
            "fdNm": {
              "#cdata-section": " 마늘비빔밥 "
            },
            "registDt": {
              "#cdata-section": " 2015-02-10 "
            },
            "rtnFileSeCode": {
              "#cdata-section": " 185002 "
            },
            "rtnFileSn": {
              "#cdata-section": " 1 "
            },
            "rtnImageDc": {
              "#cdata-section": " http://www.nongsaro.go.kr/cms_contents/114/89466_MF_ATTACH_01_TMB.png "
            },
            "rtnImgSeCode": {
              "#cdata-section": " 209001 "
            },
            "rtnOrginlFileNm": {
              "#cdata-section": " 39_0.png "
            },
            "rtnStreFileNm": {
              "#cdata-section": " 89466_MF_ATTACH_01.png "
            },
            "rtnThumbFileNm": {
              "#cdata-section": " 89466_MF_ATTACH_01_TMB.png "
            }
          },
          {
            "cntntsChargerEsntlNm": {
              "#cdata-section": " 관리자 "
            },
            "cntntsNo": {
              "#cdata-section": " 89465 "
            },
            "cntntsRdcnt": {
              "#cdata-section": " 2 "
            },
            "cntntsSj": {
              "#cdata-section": " 비 오는 날 즐겨보세요 비의 계절에 어울리는 요리 "
            },
            "dietNm": {
              "#cdata-section": " 비 오는 날 즐겨보세요 비의 계절에 어울리는 요리 "
            },
            "fdNm": {
              "#cdata-section": " 낙지칼국수 "
            },
            "registDt": {
              "#cdata-section": " 2015-02-10 "
            },
            "rtnFileSeCode": {
              "#cdata-section": " 185002 "
            },
            "rtnFileSn": {
              "#cdata-section": " 1 "
            },
            "rtnImageDc": {
              "#cdata-section": " http://www.nongsaro.go.kr/cms_contents/114/89465_MF_ATTACH_01_TMB.png "
            },
            "rtnImgSeCode": {
              "#cdata-section": " 209001 "
            },
            "rtnOrginlFileNm": {
              "#cdata-section": " 40_0.png "
            },
            "rtnStreFileNm": {
              "#cdata-section": " 89465_MF_ATTACH_01.png "
            },
            "rtnThumbFileNm": {
              "#cdata-section": " 89465_MF_ATTACH_01_TMB.png "
            }
          },
          {
            "cntntsChargerEsntlNm": {
              "#cdata-section": " 관리자 "
            },
            "cntntsNo": {
              "#cdata-section": " 89464 "
            },
            "cntntsRdcnt": {
              "#cdata-section": " 2 "
            },
            "cntntsSj": {
              "#cdata-section": " 11월 11일은 가래떡Day! "
            },
            "dietNm": {
              "#cdata-section": " 11월 11일은 가래떡Day! "
            },
            "fdNm": {
              "#cdata-section": " 가래떡국(2인분) "
            },
            "registDt": {
              "#cdata-section": " 2015-02-10 "
            },
            "rtnFileSeCode": {
              "#cdata-section": " 185002 "
            },
            "rtnFileSn": {
              "#cdata-section": " 1 "
            },
            "rtnImageDc": {
              "#cdata-section": " http://www.nongsaro.go.kr/cms_contents/114/89464_MF_ATTACH_01_TMB.png "
            },
            "rtnImgSeCode": {
              "#cdata-section": " 209001 "
            },
            "rtnOrginlFileNm": {
              "#cdata-section": " 41_0.png "
            },
            "rtnStreFileNm": {
              "#cdata-section": " 89464_MF_ATTACH_01.png "
            },
            "rtnThumbFileNm": {
              "#cdata-section": " 89464_MF_ATTACH_01_TMB.png "
            }
          },
          {
            "cntntsChargerEsntlNm": {
              "#cdata-section": " 관리자 "
            },
            "cntntsNo": {
              "#cdata-section": " 89463 "
            },
            "cntntsRdcnt": {
              "#cdata-section": " 1 "
            },
            "cntntsSj": {
              "#cdata-section": " 출산을 축하하며 <산모를 위한 요리> "
            },
            "dietNm": {
              "#cdata-section": " 출산을 축하하며 <산모를 위한 요리> "
            },
            "fdNm": {
              "#cdata-section": " 굴솥밥 "
            },
            "registDt": {
              "#cdata-section": " 2015-02-10 "
            },
            "rtnFileSeCode": {
              "#cdata-section": " 185002 "
            },
            "rtnFileSn": {
              "#cdata-section": " 1 "
            },
            "rtnImageDc": {
              "#cdata-section": " http://www.nongsaro.go.kr/cms_contents/114/89463_MF_ATTACH_01_TMB.png "
            },
            "rtnImgSeCode": {
              "#cdata-section": " 209001 "
            },
            "rtnOrginlFileNm": {
              "#cdata-section": " 42_0.png "
            },
            "rtnStreFileNm": {
              "#cdata-section": " 89463_MF_ATTACH_01.png "
            },
            "rtnThumbFileNm": {
              "#cdata-section": " 89463_MF_ATTACH_01_TMB.png "
            }
          },
          {
            "cntntsChargerEsntlNm": {
              "#cdata-section": " 관리자 "
            },
            "cntntsNo": {
              "#cdata-section": " 89462 "
            },
            "cntntsRdcnt": {
              "#cdata-section": " 2 "
            },
            "cntntsSj": {
              "#cdata-section": " 낭만 가득한 계절에 만나는 <캠핑요리> "
            },
            "dietNm": {
              "#cdata-section": " 낭만 가득한 계절에 만나는 <캠핑요리> "
            },
            "fdNm": {
              "#cdata-section": " 등갈비구이 "
            },
            "registDt": {
              "#cdata-section": " 2015-02-10 "
            },
            "rtnFileSeCode": {
              "#cdata-section": " 185002 "
            },
            "rtnFileSn": {
              "#cdata-section": " 1 "
            },
            "rtnImageDc": {
              "#cdata-section": " http://www.nongsaro.go.kr/cms_contents/114/89462_MF_ATTACH_01_TMB.png "
            },
            "rtnImgSeCode": {
              "#cdata-section": " 209001 "
            },
            "rtnOrginlFileNm": {
              "#cdata-section": " 43_0.png "
            },
            "rtnStreFileNm": {
              "#cdata-section": " 89462_MF_ATTACH_01.png "
            },
            "rtnThumbFileNm": {
              "#cdata-section": " 89462_MF_ATTACH_01_TMB.png "
            }
          },
          {
            "cntntsChargerEsntlNm": {
              "#cdata-section": " 관리자 "
            },
            "cntntsNo": {
              "#cdata-section": " 89461 "
            },
            "cntntsRdcnt": {
              "#cdata-section": " 3 "
            },
            "cntntsSj": {
              "#cdata-section": " 밤이 길어 햇살이 그리운 날 <우리네 작은 설 동지(冬至)> "
            },
            "dietNm": {
              "#cdata-section": " 밤이 길어 햇살이 그리운 날 <우리네 작은 설 동지(冬至)> "
            },
            "fdNm": {
              "#cdata-section": " 팥죽 "
            },
            "registDt": {
              "#cdata-section": " 2015-02-10 "
            },
            "rtnFileSeCode": {
              "#cdata-section": " 185002 "
            },
            "rtnFileSn": {
              "#cdata-section": " 1 "
            },
            "rtnImageDc": {
              "#cdata-section": " http://www.nongsaro.go.kr/cms_contents/114/89461_MF_ATTACH_01_TMB.png "
            },
            "rtnImgSeCode": {
              "#cdata-section": " 209001 "
            },
            "rtnOrginlFileNm": {
              "#cdata-section": " 44_0.png "
            },
            "rtnStreFileNm": {
              "#cdata-section": " 89461_MF_ATTACH_01.png "
            },
            "rtnThumbFileNm": {
              "#cdata-section": " 89461_MF_ATTACH_01_TMB.png "
            }
          },
          {
            "cntntsChargerEsntlNm": {
              "#cdata-section": " 관리자 "
            },
            "cntntsNo": {
              "#cdata-section": " 89460 "
            },
            "cntntsRdcnt": {
              "#cdata-section": " 3 "
            },
            "cntntsSj": {
              "#cdata-section": " 초보주부도 두렵지 않아 <집들이 요리> "
            },
            "dietNm": {
              "#cdata-section": " 초보주부도 두렵지 않아 <집들이 요리> "
            },
            "fdNm": {
              "#cdata-section": " 대나무통밥 "
            },
            "registDt": {
              "#cdata-section": " 2015-02-10 "
            },
            "rtnFileSeCode": {
              "#cdata-section": " 185002 "
            },
            "rtnFileSn": {
              "#cdata-section": " 1 "
            },
            "rtnImageDc": {
              "#cdata-section": " http://www.nongsaro.go.kr/cms_contents/114/89460_MF_ATTACH_01_TMB.png "
            },
            "rtnImgSeCode": {
              "#cdata-section": " 209001 "
            },
            "rtnOrginlFileNm": {
              "#cdata-section": " 45_0.png "
            },
            "rtnStreFileNm": {
              "#cdata-section": " 89460_MF_ATTACH_01.png "
            },
            "rtnThumbFileNm": {
              "#cdata-section": " 89460_MF_ATTACH_01_TMB.png "
            }
          }
        ],
        "numOfRows": "23",
        "pageNo": "1",
        "totalCount": "23"
      }
    }
  },
  "#omit-xml-declaration": "yes"
}